Tichonet_Unit10/U10_facenet_utils.py
Tichonet_Unit10/U10_style_transfer_utils.py
Tichonet_Unit10/U10_yolo3_utils.py
Tichonet_Unit10/__init__.py
Tichonet_Unit10/utils.py
Tichonet_Unit10/datasets/data.mat
Tichonet_Unit10/datasets/test_signs.h5
Tichonet_Unit10/datasets/train_signs.h5
Tichonet_Unit10/datasets/cat_nocat/test_catvnoncat.h5
Tichonet_Unit10/datasets/cat_nocat/train_catvnoncat.h5
tichonet_unit10-0.0.2.dist-info/METADATA
tichonet_unit10-0.0.2.dist-info/WHEEL
tichonet_unit10-0.0.2.dist-info/licenses/LICENSE
tichonet_unit10-0.0.2.dist-info/RECORD
