Metadata-Version: 2.1
Name: Tichonet_Unit10
Version: 0.0.2
Summary: Includes The Contents Of Gad Lidror's unit10 contents. All packed up together!
Project-URL: Homepage, https://github.com/SkipperCMD/Unit10
Author-email: TichonetDataScience - Yannay Rosenblatt <skipper.cmd@gmail.com>
License: MIT License
License-File: LICENSE
Classifier: License :: OSI Approved :: MIT License
Classifier: Operating System :: OS Independent
Classifier: Programming Language :: Python
Requires-Python: >=3.8
